{
  "facility_code": "11900132",
  "institution": "SUNY HEALTH SCIENCE CENTER AT BROOKLYN",
  "city": "BROOKLYN",
  "state": "NY",
  "country": "USA",
  "bah": 3258,
  "poe": true,
  "yr": null,
  "gibill": 8,
  "cross": 196255,
  "grad_rate": null,
  "grad_rate_rank": null,
  "default_rate": 2.1,
  "avg_stu_loan_debt": 17250,
  "avg_stu_loan_debt_rank": 823,
  "indicator_group": 1,
  "salary": null,
  "zip": "11203",
  "ope": "00283900",
  "correspondence": null,
  "flight": null,
  "calendar": "semesters",
  "tuition_in_state": null,
  "tuition_out_of_state": null,
  "student_veteran": null,
  "student_veteran_link": null
}