{
  "facility_code": "11969138",
  "institution": "INDIANA UNIVERSITY OF PENNSYLVANIA",
  "city": "INDIANA",
  "state": "PA",
  "country": "USA",
  "bah": 1431,
  "poe": true,
  "yr": true,
  "gibill": 475,
  "cross": 213020,
  "grad_rate": 50.3,
  "grad_rate_rank": 887,
  "default_rate": 8.4,
  "avg_stu_loan_debt": 20500,
  "avg_stu_loan_debt_rank": 1243,
  "indicator_group": 1,
  "salary": null,
  "zip": "15705",
  "ope": "00327700",
  "correspondence": null,
  "flight": null,
  "calendar": "semesters",
  "tuition_in_state": "8672",
  "tuition_out_of_state": "19480",
  "student_veteran": null,
  "student_veteran_link": null,
  "vetsuccess_name": null,
  "vetsuccess_email": null,
  "gijobs": null
}