{
  "facility_code": "31831210",
  "institution": "UNIVERSIDAD DEL ESTE-MIRAMAR",
  "city": "MIRAMAR",
  "state": "FL",
  "country": "USA",
  "bah": 1950,
  "poe": null,
  "yr": null,
  "gibill": null,
  "cross": 243346,
  "grad_rate": 22.5,
  "grad_rate_rank": 1678,
  "default_rate": 22.5,
  "avg_stu_loan_debt": 3500,
  "avg_stu_loan_debt_rank": 5,
  "indicator_group": 1,
  "salary": null,
  "zip": "33025",
  "ope": "00394100",
  "correspondence": null,
  "flight": null,
  "calendar": "semesters",
  "tuition_in_state": "5194",
  "tuition_out_of_state": "5194",
  "student_veteran": null,
  "student_veteran_link": null
}