{
  "facility_code": "34002611",
  "institution": "TRUETT-MCCONNELL COLLEGE",
  "city": "CLEVELAND",
  "state": "GA",
  "country": "USA",
  "bah": 975,
  "poe": null,
  "yr": true,
  "gibill": 19,
  "cross": 141237,
  "grad_rate": 9.4,
  "grad_rate_rank": 1833,
  "default_rate": 17.0,
  "avg_stu_loan_debt": 11468,
  "avg_stu_loan_debt_rank": 253,
  "indicator_group": 1,
  "salary": null,
  "zip": "30528",
  "ope": "00159700",
  "correspondence": null,
  "flight": null,
  "calendar": "semesters",
  "tuition_in_state": "15650",
  "tuition_out_of_state": "15650",
  "student_veteran": null,
  "student_veteran_link": null
}