{
  "facility_code": "21960101",
  "institution": "BROWN MACKIE COLLEGE - BIRMINGHAM",
  "city": "BIRMINGHAM",
  "state": "AL",
  "country": "USA",
  "bah": 1113,
  "poe": true,
  "yr": true,
  "gibill": 86,
  "cross": 470162,
  "grad_rate": null,
  "grad_rate_rank": null,
  "default_rate": 26.2,
  "avg_stu_loan_debt": 15000,
  "avg_stu_loan_debt_rank": 662,
  "indicator_group": 3,
  "salary": null,
  "zip": "35209",
  "ope": "04051333",
  "correspondence": null,
  "flight": null,
  "calendar": "quarters",
  "tuition_in_state": "12060",
  "tuition_out_of_state": "12060",
  "student_veteran": null,
  "student_veteran_link": null
}