{
  "facility_code": "25482210",
  "institution": "FLORIDA ACADEMY",
  "city": "FT. MYERS",
  "state": "FL",
  "country": "USA",
  "bah": 1344,
  "poe": true,
  "yr": null,
  "gibill": 12,
  "cross": 462035,
  "grad_rate": null,
  "grad_rate_rank": null,
  "default_rate": null,
  "avg_stu_loan_debt": 3167,
  "avg_stu_loan_debt_rank": 59,
  "indicator_group": 5,
  "salary": null,
  "zip": "33966",
  "ope": "04188300",
  "correspondence": null,
  "flight": null,
  "calendar": "nontraditional",
  "tuition_in_state": null,
  "tuition_out_of_state": null,
  "student_veteran": null,
  "student_veteran_link": null,
  "vetsuccess_name": null,
  "vetsuccess_email": null,
  "gijobs": null
}