{
  "facility_code": "14800411",
  "institution": "LANIER TECHNICAL COLLEGE (OAKWOOD)",
  "city": "OAKWOOD",
  "state": "GA",
  "country": "USA",
  "bah": 975,
  "poe": true,
  "yr": null,
  "gibill": 121,
  "cross": 140243,
  "grad_rate": 35.1,
  "grad_rate_rank": 494,
  "default_rate": 0.0,
  "avg_stu_loan_debt": null,
  "avg_stu_loan_debt_rank": null,
  "indicator_group": 3,
  "salary": null,
  "zip": "30566",
  "ope": "00525400",
  "correspondence": null,
  "flight": null,
  "calendar": "semesters",
  "tuition_in_state": "2246",
  "tuition_out_of_state": "4166",
  "student_veteran": null,
  "student_veteran_link": null,
  "vetsuccess_name": null,
  "vetsuccess_email": null,
  "gijobs": true
}