{
  "facility_code": "11801336",
  "institution": "UNIVERSITY OF OKLAHOMA HEALTH SCIENCES CENTER/OFFICE ADM/REC",
  "city": "OKLAHOMA CITY",
  "state": "OK",
  "country": "USA",
  "bah": 1086,
  "poe": true,
  "yr": true,
  "gibill": 88,
  "cross": 207342,
  "grad_rate": null,
  "grad_rate_rank": null,
  "default_rate": 6.9,
  "avg_stu_loan_debt": 17281,
  "avg_stu_loan_debt_rank": 830,
  "indicator_group": 1,
  "salary": null,
  "zip": "73126",
  "ope": "00318401",
  "correspondence": null,
  "flight": null,
  "calendar": "semesters",
  "tuition_in_state": null,
  "tuition_out_of_state": null,
  "student_veteran": null,
  "student_veteran_link": null
}