{
  "facility_code": "11802042",
  "institution": "UNIVERSITY OF TENNESSEE AT KNOXVILLE",
  "city": "KNOXVILLE",
  "state": "TN",
  "country": "USA",
  "bah": 1074,
  "poe": null,
  "yr": true,
  "gibill": 808,
  "cross": 221759,
  "grad_rate": 66.1,
  "grad_rate_rank": 406,
  "default_rate": 8.1,
  "avg_stu_loan_debt": 16375,
  "avg_stu_loan_debt_rank": 731,
  "indicator_group": 1,
  "salary": null,
  "zip": "37996",
  "ope": "00353000",
  "correspondence": null,
  "flight": null,
  "calendar": "semesters",
  "tuition_in_state": "9092",
  "tuition_out_of_state": "27582",
  "student_veteran": true,
  "student_veteran_link": "https://utk.collegiatelink.net/organization/VOLF",
  "vetsuccess_name": null,
  "vetsuccess_email": null,
  "gijobs": true
}