{
  "facility_code": "15552835",
  "institution": "PIONEER CAREER AND TECHNICAL CENTER",
  "city": "SHELBY",
  "state": "OH",
  "country": "USA",
  "bah": 807,
  "poe": true,
  "yr": null,
  "gibill": 3,
  "cross": 407522,
  "grad_rate": 93.5,
  "grad_rate_rank": 177,
  "default_rate": 0.0,
  "avg_stu_loan_debt": null,
  "avg_stu_loan_debt_rank": null,
  "indicator_group": 5,
  "salary": null,
  "zip": "44875",
  "ope": "02239800",
  "correspondence": null,
  "flight": null,
  "calendar": "nontraditional",
  "tuition_in_state": null,
  "tuition_out_of_state": null,
  "student_veteran": null,
  "student_veteran_link": null,
  "vetsuccess_name": null,
  "vetsuccess_email": null,
  "gijobs": null
}