{
  "facility_code": "18815230",
  "institution": "BERGEN COUNTY TECHNICAL INSTITUTE",
  "city": "HACKENSACK",
  "state": "NJ",
  "country": "USA",
  "bah": 2256,
  "poe": null,
  "yr": null,
  "gibill": 9,
  "cross": 183983,
  "grad_rate": 95.6,
  "grad_rate_rank": 139,
  "default_rate": 13.0,
  "avg_stu_loan_debt": 4170,
  "avg_stu_loan_debt_rank": 158,
  "indicator_group": 5,
  "salary": null,
  "zip": "07601",
  "ope": "02312000",
  "correspondence": null,
  "flight": null,
  "calendar": "nontraditional",
  "tuition_in_state": null,
  "tuition_out_of_state": null,
  "student_veteran": null,
  "student_veteran_link": null
}