{
  "facility_code": "25021003",
  "institution": "TUCSON COLLEGE OF BEAUTY",
  "city": "TUCSON",
  "state": "AZ",
  "country": "USA",
  "bah": 1176,
  "poe": null,
  "yr": null,
  "gibill": null,
  "cross": 447704,
  "grad_rate": 87.1,
  "grad_rate_rank": 366,
  "default_rate": 2.0,
  "avg_stu_loan_debt": 7500,
  "avg_stu_loan_debt_rank": 704,
  "indicator_group": 5,
  "salary": null,
  "zip": "85705",
  "ope": "04059300",
  "correspondence": null,
  "flight": null,
  "calendar": "nontraditional",
  "tuition_in_state": null,
  "tuition_out_of_state": null,
  "student_veteran": null,
  "student_veteran_link": null,
  "vetsuccess_name": null,
  "vetsuccess_email": null,
  "gijobs": null
}