{
  "facility_code": "25030843",
  "institution": "MIMS CLASSIC BEAUTY COLLEGE",
  "city": "SAN ANTONIO",
  "state": "TX",
  "country": "USA",
  "bah": 1398,
  "poe": null,
  "yr": null,
  "gibill": null,
  "cross": 226860,
  "grad_rate": 61.9,
  "grad_rate_rank": 1558,
  "default_rate": 83.3,
  "avg_stu_loan_debt": null,
  "avg_stu_loan_debt_rank": null,
  "indicator_group": 5,
  "salary": null,
  "zip": "78216",
  "ope": "00849800",
  "correspondence": null,
  "flight": null,
  "calendar": "nontraditional",
  "tuition_in_state": null,
  "tuition_out_of_state": null,
  "student_veteran": null,
  "student_veteran_link": null,
  "vetsuccess_name": null,
  "vetsuccess_email": null,
  "gijobs": null
}