{
  "facility_code": "25050713",
  "institution": "CONCEPT COLLEGE OF COSMETOLOGY-DANVILLE",
  "city": "DANVILLE",
  "state": "IL",
  "country": "USA",
  "bah": 1047,
  "poe": null,
  "yr": null,
  "gibill": 1,
  "cross": 144573,
  "grad_rate": 65.9,
  "grad_rate_rank": 1387,
  "default_rate": 41.5,
  "avg_stu_loan_debt": 7500,
  "avg_stu_loan_debt_rank": 704,
  "indicator_group": 5,
  "salary": null,
  "zip": "61832",
  "ope": "02317300",
  "correspondence": null,
  "flight": null,
  "calendar": "nontraditional",
  "tuition_in_state": null,
  "tuition_out_of_state": null,
  "student_veteran": null,
  "student_veteran_link": null
}