{
  "facility_code": "25067343",
  "institution": "ROYAL BEAUTY CAREERS",
  "city": "HOUSTON",
  "state": "TX",
  "country": "USA",
  "bah": 1623,
  "poe": null,
  "yr": null,
  "gibill": 10,
  "cross": 420194,
  "grad_rate": 49.2,
  "grad_rate_rank": 1968,
  "default_rate": 23.3,
  "avg_stu_loan_debt": 4833,
  "avg_stu_loan_debt_rank": 227,
  "indicator_group": 5,
  "salary": null,
  "zip": "77069",
  "ope": "03108700",
  "correspondence": null,
  "flight": null,
  "calendar": "nontraditional",
  "tuition_in_state": null,
  "tuition_out_of_state": null,
  "student_veteran": null,
  "student_veteran_link": null,
  "vetsuccess_name": null,
  "vetsuccess_email": null,
  "gijobs": null
}