{
  "facility_code": "34904415",
  "institution": "AIB COLLEGE OF BUSINESS",
  "city": "DES MOINES",
  "state": "IA",
  "country": "USA",
  "bah": 1230,
  "poe": true,
  "yr": null,
  "gibill": 40,
  "cross": 152822,
  "grad_rate": null,
  "grad_rate_rank": null,
  "default_rate": 12.2,
  "avg_stu_loan_debt": 17667,
  "avg_stu_loan_debt_rank": 884,
  "indicator_group": 1,
  "salary": null,
  "zip": "50321",
  "ope": "00396300",
  "correspondence": null,
  "flight": null,
  "calendar": "quarters",
  "tuition_in_state": "14067",
  "tuition_out_of_state": "14067",
  "student_veteran": null,
  "student_veteran_link": null,
  "vetsuccess_name": null,
  "vetsuccess_email": null,
  "gijobs": null
}