{
  "facility_code": "35022618",
  "institution": "UNITED THEOLOGICAL SEMINARY & BIBLE COLL",
  "city": "MONROE",
  "state": "LA",
  "country": "USA",
  "bah": 870,
  "poe": null,
  "yr": null,
  "gibill": 3,
  "cross": 206288,
  "grad_rate": null,
  "grad_rate_rank": null,
  "default_rate": 2.7,
  "avg_stu_loan_debt": null,
  "avg_stu_loan_debt_rank": null,
  "indicator_group": 4,
  "salary": null,
  "zip": "71201",
  "ope": "00312200",
  "correspondence": null,
  "flight": null,
  "calendar": "semesters",
  "tuition_in_state": null,
  "tuition_out_of_state": null,
  "student_veteran": null,
  "student_veteran_link": null,
  "vetsuccess_name": null,
  "vetsuccess_email": null,
  "gijobs": null
}