{
  "facility_code": "25539935",
  "institution": "TIFFIN ACADEMY OF HAIR DESIGN",
  "city": "TIFFIN",
  "state": "OH",
  "country": "USA",
  "bah": 1005,
  "poe": null,
  "yr": null,
  "gibill": null,
  "cross": 206039,
  "grad_rate": 63.9,
  "grad_rate_rank": 1474,
  "default_rate": 6.9,
  "avg_stu_loan_debt": 7170,
  "avg_stu_loan_debt_rank": 654,
  "indicator_group": 5,
  "salary": null,
  "zip": "44883",
  "ope": "00966000",
  "correspondence": null,
  "flight": null,
  "calendar": "nontraditional",
  "tuition_in_state": "12925",
  "tuition_out_of_state": "12925",
  "student_veteran": null,
  "student_veteran_link": null,
  "vetsuccess_name": null,
  "vetsuccess_email": null,
  "gijobs": null
}