{
  "facility_code": "24020643",
  "institution": "WADE COLLEGE",
  "city": "DALLAS",
  "state": "TX",
  "country": "USA",
  "bah": 1611,
  "poe": null,
  "yr": null,
  "gibill": 9,
  "cross": 226879,
  "grad_rate": 50.0,
  "grad_rate_rank": 263,
  "default_rate": 13.3,
  "avg_stu_loan_debt": 17707,
  "avg_stu_loan_debt_rank": 1116,
  "indicator_group": 2,
  "salary": null,
  "zip": "75207",
  "ope": "01013000",
  "correspondence": null,
  "flight": null,
  "calendar": "nontraditional",
  "tuition_in_state": "12163",
  "tuition_out_of_state": "12163",
  "student_veteran": null,
  "student_veteran_link": null
}