{
  "facility_code": "31001038",
  "institution": "DICKINSON COLLEGE",
  "city": "CARLISLE",
  "state": "PA",
  "country": "USA",
  "bah": 1335,
  "poe": null,
  "yr": true,
  "gibill": 22,
  "cross": 212009,
  "grad_rate": 84.6,
  "grad_rate_rank": 102,
  "default_rate": 1.8,
  "avg_stu_loan_debt": 21901,
  "avg_stu_loan_debt_rank": 1407,
  "indicator_group": 1,
  "salary": null,
  "zip": "17013",
  "ope": "00325300",
  "correspondence": null,
  "flight": null,
  "calendar": "semesters",
  "tuition_in_state": "44551",
  "tuition_out_of_state": "44551",
  "student_veteran": null,
  "student_veteran_link": null
}