{
  "facility_code": "31000921",
  "institution": "COLLEGE OF THE HOLY CROSS",
  "city": "WORCESTER",
  "state": "MA",
  "country": "USA",
  "bah": 1497,
  "poe": null,
  "yr": true,
  "gibill": 16,
  "cross": 166124,
  "grad_rate": 92.9,
  "grad_rate_rank": 34,
  "default_rate": 1.8,
  "avg_stu_loan_debt": 27000,
  "avg_stu_loan_debt_rank": 1868,
  "indicator_group": 1,
  "salary": null,
  "zip": "01610",
  "ope": "00214100",
  "correspondence": null,
  "flight": null,
  "calendar": "semesters",
  "tuition_in_state": "43400",
  "tuition_out_of_state": "43400",
  "student_veteran": null,
  "student_veteran_link": null,
  "vetsuccess_name": null,
  "vetsuccess_email": null,
  "gijobs": null
}