{
  "facility_code": "31001042",
  "institution": "MILLIGAN COLLEGE",
  "city": "MILLIGAN COLLEGE",
  "state": "TN",
  "country": "USA",
  "bah": 981,
  "poe": true,
  "yr": true,
  "gibill": 26,
  "cross": 221014,
  "grad_rate": 59.6,
  "grad_rate_rank": 575,
  "default_rate": 7.7,
  "avg_stu_loan_debt": 18934,
  "avg_stu_loan_debt_rank": 1050,
  "indicator_group": 1,
  "salary": null,
  "zip": "37682",
  "ope": "00351100",
  "correspondence": null,
  "flight": null,
  "calendar": "semesters",
  "tuition_in_state": "26760",
  "tuition_out_of_state": "26760",
  "student_veteran": null,
  "student_veteran_link": null,
  "vetsuccess_name": null,
  "vetsuccess_email": null,
  "gijobs": null
}