{
  "facility_code": "31000411",
  "institution": "BRENAU UNIVERSITY",
  "city": "GAINESVILLE",
  "state": "GA",
  "country": "USA",
  "bah": 975,
  "poe": true,
  "yr": true,
  "gibill": 213,
  "cross": 139199,
  "grad_rate": 44.9,
  "grad_rate_rank": 1069,
  "default_rate": 7.5,
  "avg_stu_loan_debt": 19213,
  "avg_stu_loan_debt_rank": 1100,
  "indicator_group": 1,
  "salary": null,
  "zip": "30501",
  "ope": "00155600",
  "correspondence": null,
  "flight": null,
  "calendar": "semesters",
  "tuition_in_state": "22168",
  "tuition_out_of_state": "22168",
  "student_veteran": null,
  "student_veteran_link": null,
  "vetsuccess_name": null,
  "vetsuccess_email": null,
  "gijobs": null
}