{
  "facility_code": "31014523",
  "institution": "BETHANY LUTHERAN COLLEGE",
  "city": "MANKATO",
  "state": "MN",
  "country": "USA",
  "bah": 1200,
  "poe": null,
  "yr": true,
  "gibill": 15,
  "cross": 173142,
  "grad_rate": 51.1,
  "grad_rate_rank": 863,
  "default_rate": 6.9,
  "avg_stu_loan_debt": 19750,
  "avg_stu_loan_debt_rank": 1157,
  "indicator_group": 1,
  "salary": null,
  "zip": "56001",
  "ope": "00233700",
  "correspondence": null,
  "flight": null,
  "calendar": "semesters",
  "tuition_in_state": "23270",
  "tuition_out_of_state": "23270",
  "student_veteran": null,
  "student_veteran_link": null,
  "vetsuccess_name": null,
  "vetsuccess_email": null,
  "gijobs": null
}