{
  "facility_code": "31012019",
  "institution": "COLBY COLLEGE",
  "city": "WATERVILLE",
  "state": "ME",
  "country": "USA",
  "bah": 1026,
  "poe": null,
  "yr": true,
  "gibill": 4,
  "cross": 161086,
  "grad_rate": 90.3,
  "grad_rate_rank": 60,
  "default_rate": 2.1,
  "avg_stu_loan_debt": 20840,
  "avg_stu_loan_debt_rank": 1296,
  "indicator_group": 1,
  "salary": null,
  "zip": "04901",
  "ope": "00203900",
  "correspondence": null,
  "flight": null,
  "calendar": "nontraditional",
  "tuition_in_state": "44320",
  "tuition_out_of_state": "44320",
  "student_veteran": null,
  "student_veteran_link": null
}