{
  "facility_code": "24801429",
  "institution": "MOUNT WASHINGTON COLLEGE - SALEM",
  "city": "SALEM",
  "state": "NH",
  "country": "USA",
  "bah": 1413,
  "poe": true,
  "yr": true,
  "gibill": 28,
  "cross": 182865,
  "grad_rate": 31.1,
  "grad_rate_rank": 603,
  "default_rate": 20.2,
  "avg_stu_loan_debt": 11015,
  "avg_stu_loan_debt_rank": 782,
  "indicator_group": 2,
  "salary": null,
  "zip": "03079",
  "ope": "00472900",
  "correspondence": null,
  "flight": null,
  "calendar": "nontraditional",
  "tuition_in_state": "11964",
  "tuition_out_of_state": "11964",
  "student_veteran": null,
  "student_veteran_link": null,
  "vetsuccess_name": null,
  "vetsuccess_email": null,
  "gijobs": null
}