{
  "facility_code": "25200422",
  "institution": "ROSS MEDICAL EDUCATION CENTER-ROOSEVELT PARK",
  "city": "ROOSEVELT PARK",
  "state": "MI",
  "country": "USA",
  "bah": 903,
  "poe": null,
  "yr": null,
  "gibill": 5,
  "cross": 365824,
  "grad_rate": 92.4,
  "grad_rate_rank": 207,
  "default_rate": 25.7,
  "avg_stu_loan_debt": 9500,
  "avg_stu_loan_debt_rank": 1075,
  "indicator_group": 5,
  "salary": null,
  "zip": "49441",
  "ope": "02099703",
  "correspondence": null,
  "flight": null,
  "calendar": "nontraditional",
  "tuition_in_state": null,
  "tuition_out_of_state": null,
  "student_veteran": null,
  "student_veteran_link": null,
  "vetsuccess_name": null,
  "vetsuccess_email": null,
  "gijobs": null
}