{
  "facility_code": "31902029",
  "institution": "RIVIER UNIVERSITY",
  "city": "NASHUA",
  "state": "NH",
  "country": "USA",
  "bah": 1539,
  "poe": true,
  "yr": true,
  "gibill": 62,
  "cross": 183211,
  "grad_rate": 51.0,
  "grad_rate_rank": 867,
  "default_rate": 5.9,
  "avg_stu_loan_debt": 25500,
  "avg_stu_loan_debt_rank": 1807,
  "indicator_group": 1,
  "salary": null,
  "zip": "03060",
  "ope": "00258600",
  "correspondence": null,
  "flight": null,
  "calendar": "semesters",
  "tuition_in_state": "26905",
  "tuition_out_of_state": "26905",
  "student_veteran": null,
  "student_veteran_link": null,
  "vetsuccess_name": null,
  "vetsuccess_email": null,
  "gijobs": null
}