{
  "facility_code": "31997138",
  "institution": "DELAWARE VALLEY COLLEGE",
  "city": "DOYLESTOWN",
  "state": "PA",
  "country": "USA",
  "bah": 2025,
  "poe": null,
  "yr": true,
  "gibill": 78,
  "cross": 211981,
  "grad_rate": 58.1,
  "grad_rate_rank": 624,
  "default_rate": 7.5,
  "avg_stu_loan_debt": 23384,
  "avg_stu_loan_debt_rank": 1568,
  "indicator_group": 1,
  "salary": null,
  "zip": "18901",
  "ope": "00325200",
  "correspondence": null,
  "flight": null,
  "calendar": "semesters",
  "tuition_in_state": "31746",
  "tuition_out_of_state": "31746",
  "student_veteran": true,
  "student_veteran_link": "http://www.studentveterans.org ",
  "vetsuccess_name": null,
  "vetsuccess_email": null,
  "gijobs": null
}