{
  "facility_code": "24906414",
  "institution": "HARRISON COLLEGE - TERRE HAUTE",
  "city": "TERRE HAUTE",
  "state": "IN",
  "country": "USA",
  "bah": 1071,
  "poe": true,
  "yr": true,
  "gibill": 24,
  "cross": 151166,
  "grad_rate": 29.2,
  "grad_rate_rank": 654,
  "default_rate": 21.6,
  "avg_stu_loan_debt": 11964,
  "avg_stu_loan_debt_rank": 844,
  "indicator_group": 2,
  "salary": null,
  "zip": "47803",
  "ope": "02158400",
  "correspondence": null,
  "flight": null,
  "calendar": "quarters",
  "tuition_in_state": "16050",
  "tuition_out_of_state": "16050",
  "student_veteran": null,
  "student_veteran_link": null,
  "vetsuccess_name": null,
  "vetsuccess_email": null,
  "gijobs": null
}