{
  "facility_code": "24919414",
  "institution": "KAPLAN COLLEGE - MERRILLVILLE",
  "city": "MERRILLVILLE",
  "state": "IN",
  "country": "USA",
  "bah": 1152,
  "poe": true,
  "yr": null,
  "gibill": null,
  "cross": 152424,
  "grad_rate": null,
  "grad_rate_rank": null,
  "default_rate": null,
  "avg_stu_loan_debt": null,
  "avg_stu_loan_debt_rank": null,
  "indicator_group": null,
  "salary": null,
  "zip": "46410",
  "ope": "02201802",
  "correspondence": null,
  "flight": null,
  "calendar": "nontraditional",
  "tuition_in_state": null,
  "tuition_out_of_state": null,
  "student_veteran": null,
  "student_veteran_link": null,
  "vetsuccess_name": null,
  "vetsuccess_email": null,
  "gijobs": null
}