{
  "facility_code": "24946025",
  "institution": "ST. LOUIS COLLEGE OF HEALTH CAREERS (METRO)",
  "city": "ST. LOUIS",
  "state": "MO",
  "country": "USA",
  "bah": 1332,
  "poe": true,
  "yr": null,
  "gibill": 17,
  "cross": 179511,
  "grad_rate": 62.5,
  "grad_rate_rank": 269,
  "default_rate": 22.2,
  "avg_stu_loan_debt": 9500,
  "avg_stu_loan_debt_rank": 361,
  "indicator_group": 3,
  "salary": null,
  "zip": "63110",
  "ope": "02340500",
  "correspondence": null,
  "flight": null,
  "calendar": "semesters",
  "tuition_in_state": "19650",
  "tuition_out_of_state": "19650",
  "student_veteran": null,
  "student_veteran_link": null,
  "vetsuccess_name": null,
  "vetsuccess_email": null,
  "gijobs": null
}