{
  "facility_code": "14916447",
  "institution": "WALLA WALLA COMMUNITY COLLEGE",
  "city": "WALLA WALLA",
  "state": "WA",
  "country": "USA",
  "bah": 1185,
  "poe": true,
  "yr": true,
  "gibill": 211,
  "cross": 236887,
  "grad_rate": 37.9,
  "grad_rate_rank": 472,
  "default_rate": 23.3,
  "avg_stu_loan_debt": 9500,
  "avg_stu_loan_debt_rank": 361,
  "indicator_group": 3,
  "salary": null,
  "zip": "99362",
  "ope": "00500600",
  "correspondence": null,
  "flight": null,
  "calendar": "quarters",
  "tuition_in_state": "3898",
  "tuition_out_of_state": "5192",
  "student_veteran": null,
  "student_veteran_link": null,
  "vetsuccess_name": null,
  "vetsuccess_email": null,
  "gijobs": null
}