{
  "facility_code": "14969405",
  "institution": "COSUMNES RIVER COLLEGE",
  "city": "SACRAMENTO",
  "state": "CA",
  "country": "USA",
  "bah": 1806,
  "poe": true,
  "yr": null,
  "gibill": 370,
  "cross": 113096,
  "grad_rate": 19.8,
  "grad_rate_rank": 947,
  "default_rate": 23.1,
  "avg_stu_loan_debt": 6500,
  "avg_stu_loan_debt_rank": 385,
  "indicator_group": 2,
  "salary": null,
  "zip": "95823",
  "ope": "00753600",
  "correspondence": null,
  "flight": null,
  "calendar": "semesters",
  "tuition_in_state": "1104",
  "tuition_out_of_state": "7200",
  "student_veteran": null,
  "student_veteran_link": null
}