{
  "facility_code": "149A0405",
  "institution": "SADDLEBACK COLLEGE",
  "city": "MISSION VIEJO",
  "state": "CA",
  "country": "USA",
  "bah": 2292,
  "poe": true,
  "yr": null,
  "gibill": 677,
  "cross": 122205,
  "grad_rate": 35.1,
  "grad_rate_rank": 494,
  "default_rate": 16.0,
  "avg_stu_loan_debt": 5500,
  "avg_stu_loan_debt_rank": 117,
  "indicator_group": 3,
  "salary": null,
  "zip": "92692",
  "ope": "00891800",
  "correspondence": null,
  "flight": null,
  "calendar": "semesters",
  "tuition_in_state": "762",
  "tuition_out_of_state": "4694",
  "student_veteran": true,
  "student_veteran_link": "http://www.facebook.com/groups/152378814785860/"
}