{
  "facility_code": "25378032",
  "institution": "STAR CAREER ACADEMY - SYOSSETT",
  "city": "SYOSSETT",
  "state": "NY",
  "country": "USA",
  "bah": 2343,
  "poe": true,
  "yr": null,
  "gibill": 14,
  "cross": 437529,
  "grad_rate": 83.4,
  "grad_rate_rank": 500,
  "default_rate": 27.0,
  "avg_stu_loan_debt": 9500,
  "avg_stu_loan_debt_rank": 1075,
  "indicator_group": 5,
  "salary": null,
  "zip": "11791",
  "ope": "03380300",
  "correspondence": null,
  "flight": null,
  "calendar": "nontraditional",
  "tuition_in_state": null,
  "tuition_out_of_state": null,
  "student_veteran": null,
  "student_veteran_link": null,
  "vetsuccess_name": null,
  "vetsuccess_email": null,
  "gijobs": null
}